altparse/__init__.py
altparse/core.py
altparse/errors.py
altparse/helpers.py
altparse/model.py
altparse/parsers.py
altparse/ipautil/__init__.py
altparse/ipautil/core.py
altparse/ipautil/errors.py
altparse/ipautil/helpers.py
altparse/ipautil/model.py
altparse-0.3.0.dist-info/LICENSE.txt
altparse-0.3.0.dist-info/METADATA
altparse-0.3.0.dist-info/WHEEL
altparse-0.3.0.dist-info/top_level.txt
altparse-0.3.0.dist-info/RECORD
