Metadata-Version: 2.1
Name: altparse
Version: 0.3.0
Summary: Designed to aid in creating and maintaining AltSources
Author-email: Noah Keck <noahkeck@mindspring.com>
License: MIT License
Project-URL: homepage, https://github.com/noah978/AltSourceParser
Project-URL: repository, https://github.com/noah978/AltSourceParser
Project-URL: issues, https://github.com/noah978/AltSourceParser/issues
Project-URL: docs, https://github.com/noah978/AltSourceParser
Keywords: altstore,altsource,ios,developer
Classifier: Programming Language :: Python :: 3
Classifier: License :: OSI Approved :: MIT License
Classifier: Operating System :: OS Independent
Requires-Python: >=3.10
License-File: LICENSE.txt
Requires-Dist: requests (>=2.28.0)
Requires-Dist: github3.py (>=3.2.0)
Requires-Dist: packaging (==21.*)
